{
  "project_info": {
    "project_number": "1039933143690",
    "firebase_url": "https://amia-flutter.firebaseio.com",
    "project_id": "amia-flutter",
    "storage_bucket": "amia-flutter.appspot.com"
  },
  "client": [
    {
      "client_info": {
        "mobilesdk_app_id": "1:1039933143690:android:cf8dc34129a39644804b73",
        "android_client_info": {
          "package_name": "com.amia.amia_flutter"
        }
      },
      "oauth_client": [
        {
          "client_id": "1039933143690-houme8vofpaa3q8bri4clrag4c6mconi.apps.googleusercontent.com",
          "client_type": 1,
          "android_info": {
            "package_name": "com.amia.amia_flutter",
            "certificate_hash": "706fee551d06f90f67673719354a56cbf78296b3"
          }
        },
        {
          "client_id": "1039933143690-m49luc7j866qdl7tepg3j986rldrsjod.apps.googleusercontent.com",
          "client_type": 3
        }
      ],
      "api_key": [
        {
          "current_key": "AIzaSyCd1akuDGLVTF2FNr_AdnK6ShnCAVp5WOE"
        }
      ],
      "services": {
        "appinvite_service": {
          "other_platform_oauth_client": [
            {
              "client_id": "1039933143690-m49luc7j866qdl7tepg3j986rldrsjod.apps.googleusercontent.com",
              "client_type": 3
            },
            {
              "client_id": "1039933143690-cht2kthg4v50qfvapg78ogo9ikvjt29s.apps.googleusercontent.com",
              "client_type": 2,
              "ios_info": {
                "bundle_id": "com.amia.amiaFlutter"
              }
            }
          ]
        }
      }
    }
  ],
  "configuration_version": "1"
}